{
  "step": 4,
  "thought": "The current screen is the Bedtime tab, but we need to set an alarm. I should switch to the Alarm tab using the bottom navigation bar. The 'Alarm' tab is visible and clickable in the navigation bar.",
  "python_code": "driver.click_text(\"Alarm\")",
  "bash_command": "",
  "command_text": "driver.click_text(\"Alarm\")",
  "raw_response": {
    "done": false,
    "final_response": "",
    "python_code": "driver.click_text(\"Alarm\")",
    "thought": "The current screen is the Bedtime tab, but we need to set an alarm. I should switch to the Alarm tab using the bottom navigation bar. The 'Alarm' tab is visible and clickable in the navigation bar."
  },
  "done": false,
  "final_response": "",
  "outputs": [
    {
      "output": "",
      "returncode": 0,
      "exception_info": "",
      "observation": {
        "success": true,
        "exception": "",
        "platform": "android",
        "backend": "uiautomator2",
        "device_info": {
          "currentPackageName": "com.google.android.deskclock",
          "displayHeight": 2400,
          "displayRotation": 0,
          "displaySizeDpX": 411,
          "displaySizeDpY": 914,
          "displayWidth": 1080,
          "productName": "sdk_gphone64_x86_64",
          "screenOn": true,
          "sdkInt": 34,
          "naturalOrientation": true
        },
        "current_app": {
          "package": "com.google.android.deskclock",
          "activity": "com.android.deskclock.DeskClock"
        },
        "previous_activity": "com.android.deskclock.DeskClock",
        "activity_changed": false,
        "screenshot_path": "outputs/default/android_20260614_220946/screenshots/step_0004.png",
        "hierarchy_path": "outputs/default/android_20260614_220946/hierarchy/step_0004.xml",
        "ui_snapshot": "Android UI hierarchy\n  - FrameLayout id=\"com.android.systemui:id/status_bar_launch_animation_container\" bounds=[0,0][1080,132] center=(540,66)\n  - FrameLayout id=\"com.android.systemui:id/status_bar_container\" bounds=[0,0][1080,132] center=(540,66)\n    - FrameLayout id=\"com.android.systemui:id/status_bar\" bounds=[0,0][1080,132] center=(540,66)\n      - LinearLayout id=\"com.android.systemui:id/status_bar_contents\" bounds=[0,0][1027,132] center=(513,66)\n        - FrameLayout id=\"com.android.systemui:id/status_bar_start_side_container\" bounds=[42,1][463,132] center=(252,66)\n          - FrameLayout id=\"com.android.systemui:id/status_bar_start_side_content\" bounds=[42,1][207,132] center=(124,66)\n            - LinearLayout id=\"com.android.systemui:id/status_bar_start_side_except_heads_up\" bounds=[42,1][207,132] center=(124,66)\n              - TextView text=\"10:11\" desc=\"10:11 PM\" id=\"com.android.systemui:id/clock\" bounds=[42,1][149,132] center=(95,66)\n              - FrameLayout id=\"com.android.systemui:id/notification_icon_area\" bounds=[149,1][207,132] center=(178,66)\n                - ViewGroup id=\"com.android.systemui:id/notificationIcons\" bounds=[149,1][207,132] center=(178,66)\n                  - ImageView desc=\"Android System notification:\" bounds=[149,1][207,132] center=(178,66)\n        - View id=\"com.android.systemui:id/cutout_space_view\" bounds=[463,1][585,132] center=(524,66)\n        - FrameLayout id=\"com.android.systemui:id/status_bar_end_side_container\" bounds=[585,1][1006,132] center=(795,66)\n          - LinearLayout id=\"com.android.systemui:id/status_bar_end_side_content\" bounds=[885,1][1006,132] center=(945,66)\n            - LinearLayout id=\"com.android.systemui:id/system_icons\" bounds=[885,1][1006,132] center=(945,66)\n              - LinearLayout id=\"com.android.systemui:id/statusIcons\" bounds=[885,1][986,132] center=(935,66)\n                - FrameLayout id=\"com.android.systemui:id/wifi_combo\" bounds=[885,37][931,95] center=(908,66)\n                  - LinearLayout id=\"com.android.systemui:id/wifi_group\" bounds=[892,37][931,95] center=(911,66)\n                    - FrameLayout id=\"com.android.systemui:id/wifi_combo\" bounds=[892,46][931,85] center=(911,65)\n                      - ImageView desc=\"Wifi signal full.,No internet\" id=\"com.android.systemui:id/wifi_signal\" bounds=[892,46][931,85] center=(911,65)\n                - FrameLayout desc=\"Phone signal full.\" id=\"com.android.systemui:id/mobile_combo\" bounds=[931,37][970,95] center=(950,66)\n                  - LinearLayout id=\"com.android.systemui:id/mobile_group\" bounds=[931,37][970,95] center=(950,66)\n                      - ImageView id=\"com.android.systemui:id/mobile_signal\" bounds=[931,46][970,85] center=(950,65)\n              - LinearLayout desc=\"Battery 100 percent.\" id=\"com.android.systemui:id/battery\" bounds=[986,1][1006,132] center=(996,66)\n      - LinearLayout id=\"com.google.android.deskclock:id/action_bar_root\" bounds=[0,0][1080,2400] center=(540,1200)\n        - FrameLayout id=\"android:id/content\" bounds=[0,0][1080,2400] center=(540,1200)\n            - ViewGroup id=\"com.google.android.deskclock:id/content\" bounds=[0,0][1080,2400] center=(540,1200)\n              - LinearLayout id=\"com.google.android.deskclock:id/app_bar_layout\" bounds=[0,0][1080,300] center=(540,150)\n                - ViewGroup id=\"com.google.android.deskclock:id/toolbar\" bounds=[0,132][1080,300] center=(540,216)\n                  - TextView text=\"Alarm\" id=\"com.google.android.deskclock:id/action_bar_title\" bounds=[63,179][218,252] center=(140,215)\n                    - ImageView desc=\"More options\" id=\"com.google.android.deskclock:id/overflow_action_button\" clickable=true bounds=[975,152][1080,278] center=(1027,215)\n              - ViewGroup id=\"com.google.android.deskclock:id/desk_clock_pager_frame\" bounds=[0,300][1080,2127] center=(540,1213)\n                - ViewGroup id=\"com.google.android.deskclock:id/desk_clock_pager\" bounds=[0,300][1080,2127] center=(540,1213)\n                      - FrameLayout id=\"com.google.android.deskclock:id/main\" bounds=[0,300][1080,2127] center=(540,1213)\n                        - RecyclerView id=\"com.google.android.deskclock:id/alarm_recycler_view\" bounds=[0,300][1080,2127] center=(540,1213)\n                          - CardView desc=\"Alarm\" clickable=true bounds=[42,321][1038,648] center=(540,484)\n                            - ViewGroup id=\"com.google.android.deskclock:id/alarm_card_layout\" bounds=[42,321][1038,648] center=(540,484)\n                              - TextView text=\"8:30 AM\" desc=\"8:30 AM\" id=\"com.google.android.deskclock:id/digital_clock\" clickable=true bounds=[84,363][440,522] center=(262,442)\n                              - ImageButton desc=\"Expand alarm\" id=\"com.google.android.deskclock:id/arrow\" clickable=true bounds=[891,321][996,447] center=(943,384)\n                              - LinearLayout id=\"com.google.android.deskclock:id/alarm_info\" bounds=[84,522][850,648] center=(467,585)\n                                - TextView text=\"Mon, Tue, Wed, Thu, Fri\" desc=\"Monday, Tuesday, Wednesday, Thursday, Friday\" id=\"com.google.android.deskclock:id/days_of_week\" bounds=[84,522][492,648] center=(288,585)\n                              - Switch id=\"com.google.android.deskclock:id/onoff\" clickable=true bounds=[850,522][996,648] center=(923,585)\n                          - CardView desc=\"Alarm\" clickable=true bounds=[42,669][1038,996] center=(540,832)\n                            - ViewGroup id=\"com.google.android.deskclock:id/alarm_card_layout\" bounds=[42,669][1038,996] center=(540,832)\n                              - TextView text=\"9:00 AM\" desc=\"9:00 AM\" id=\"com.google.android.deskclock:id/digital_clock\" clickable=true bounds=[84,711][440,870] center=(262,790)\n                              - ImageButton desc=\"Expand alarm\" id=\"com.google.android.deskclock:id/arrow\" clickable=true bounds=[891,669][996,795] center=(943,732)\n                              - LinearLayout id=\"com.google.android.deskclock:id/alarm_info\" bounds=[84,870][850,996] center=(467,933)\n                                - TextView text=\"Sun, Mon, Sat\" desc=\"Sunday, Monday, Saturday\" id=\"com.google.android.deskclock:id/days_of_week\" bounds=[84,870][334,996] center=(209,933)\n                              - Switch id=\"com.google.android.deskclock:id/onoff\" clickable=true bounds=[850,870][996,996] center=(923,933)\n                - ViewGroup id=\"com.google.android.deskclock:id/fab_container\" bounds=[0,1791][1080,2127] center=(540,1959)\n                  - Button desc=\"Add alarm\" id=\"com.google.android.deskclock:id/fab\" clickable=true bounds=[414,1833][666,2085] center=(540,1959)\n              - FrameLayout id=\"com.google.android.deskclock:id/navigation_bar\" bounds=[0,2127][1080,2400] center=(540,2263)\n                  - FrameLayout desc=\"Alarm\" id=\"com.google.android.deskclock:id/tab_menu_alarm\" selected=true bounds=[0,2127][216,2337] center=(108,2232)\n                    - FrameLayout id=\"com.google.android.deskclock:id/navigation_bar_item_icon_container\" selected=true bounds=[24,2159][192,2243] center=(108,2201)\n                      - View id=\"com.google.android.deskclock:id/navigation_bar_item_active_indicator_view\" selected=true bounds=[24,2159][192,2243] center=(108,2201)\n                      - ImageView id=\"com.google.android.deskclock:id/navigation_bar_item_icon_view\" selected=true bounds=[76,2169][139,2232] center=(107,2200)\n                    - ViewGroup id=\"com.google.android.deskclock:id/navigation_bar_item_labels_group\" selected=true bounds=[57,2253][159,2337] center=(108,2295)\n                      - TextView text=\"Alarm\" id=\"com.google.android.deskclock:id/navigation_bar_item_large_label_view\" selected=true bounds=[57,2253][159,2306] center=(108,2279)\n                  - FrameLayout desc=\"Clock\" id=\"com.google.android.deskclock:id/tab_menu_clock\" clickable=true bounds=[216,2127][432,2337] center=(324,2232)\n                    - FrameLayout id=\"com.google.android.deskclock:id/navigation_bar_item_icon_container\" bounds=[240,2159][408,2243] center=(324,2201)\n                      - ImageView id=\"com.google.android.deskclock:id/navigation_bar_item_icon_view\" bounds=[292,2169][355,2232] center=(323,2200)\n                    - ViewGroup id=\"com.google.android.deskclock:id/navigation_bar_item_labels_group\" bounds=[274,2253][373,2337] center=(323,2295)\n                      - TextView text=\"Clock\" id=\"com.google.android.deskclock:id/navigation_bar_item_small_label_view\" bounds=[274,2253][373,2306] center=(323,2279)\n                  - FrameLayout desc=\"Timer\" id=\"com.google.android.deskclock:id/tab_menu_timer\" clickable=true bounds=[432,2127][648,2337] center=(540,2232)\n                    - FrameLayout id=\"com.google.android.deskclock:id/navigation_bar_item_icon_container\" bounds=[456,2159][624,2243] center=(540,2201)\n                      - ImageView id=\"com.google.android.deskclock:id/navigation_bar_item_icon_view\" bounds=[508,2169][571,2232] center=(539,2200)\n                    - ViewGroup id=\"com.google.android.deskclock:id/navigation_bar_item_labels_group\" bounds=[490,2253][589,2337] center=(539,2295)\n                      - TextView text=\"Timer\" id=\"com.google.android.deskclock:id/navigation_bar_item_small_label_view\" bounds=[490,2253][589,2306] center=(539,2279)\n                  - FrameLayout desc=\"Stopwatch\" id=\"com.google.android.deskclock:id/tab_menu_stopwatch\" clickable=true bounds=[648,2127][864,2337] center=(756,2232)\n                    - FrameLayout id=\"com.google.android.deskclock:id/navigation_bar_item_icon_container\" bounds=[672,2159][840,2243] center=(756,2201)\n                      - ImageView id=\"com.google.android.deskclock:id/navigation_bar_item_icon_view\" bounds=[724,2169][787,2232] center=(755,2200)\n                    - ViewGroup id=\"com.google.android.deskclock:id/navigation_bar_item_labels_group\" bounds=[663,2253][849,2337] center=(756,2295)\n                      - TextView text=\"Stopwatch\" id=\"com.google.android.deskclock:id/navigation_bar_item_small_label_view\" bounds=[663,2253][849,2306] center=(756,2279)\n                  - FrameLayout desc=\"Bedtime\" id=\"com.google.android.deskclock:id/tab_menu_bedtime\" clickable=true bounds=[864,2127][1080,2337] center=(972,2232)\n                    - FrameLayout id=\"com.google.android.deskclock:id/navigation_bar_item_icon_container\" bounds=[888,2159][1056,2243] center=(972,2201)\n                      - ImageView id=\"com.google.android.deskclock:id/navigation_bar_item_icon_view\" bounds=[940,2169][1003,2232] center=(971,2200)\n                    - ViewGroup id=\"com.google.android.deskclock:id/navigation_bar_item_labels_group\" bounds=[899,2253][1044,2337] center=(971,2295)\n                      - TextView text=\"Bedtime\" id=\"com.google.android.deskclock:id/navigation_bar_item_small_label_view\" bounds=[899,2253][1044,2306] center=(971,2279)",
        "python_code": "driver.click_text(\"Alarm\")",
        "python_output": "",
        "url": "",
        "title": "com.android.deskclock.DeskClock",
        "aria_snapshot": "",
        "console_output": "",
        "recent_console": ""
      }
    }
  ]
}